allure_pytest_il/__init__.py
allure_pytest_il/compat.py
allure_pytest_il/helper.py
allure_pytest_il/listener.py
allure_pytest_il/plugin.py
allure_pytest_il/utils.py
allure_pytest_il-0.0.1.dist-info/METADATA
allure_pytest_il-0.0.1.dist-info/WHEEL
allure_pytest_il-0.0.1.dist-info/entry_points.txt
allure_pytest_il-0.0.1.dist-info/top_level.txt
allure_pytest_il-0.0.1.dist-info/RECORD
